fds/__init__.py
fds/sdk/__init__.py
fds/sdk/RealTimeTimeSeries/__init__.py
fds/sdk/RealTimeTimeSeries/api_client.py
fds/sdk/RealTimeTimeSeries/configuration.py
fds/sdk/RealTimeTimeSeries/exceptions.py
fds/sdk/RealTimeTimeSeries/model_utils.py
fds/sdk/RealTimeTimeSeries/rest.py
fds/sdk/RealTimeTimeSeries/api/__init__.py
fds/sdk/RealTimeTimeSeries/api/prices_api.py
fds/sdk/RealTimeTimeSeries/api/vendor_api.py
fds/sdk/RealTimeTimeSeries/apis/__init__.py
fds/sdk/RealTimeTimeSeries/model/__init__.py
fds/sdk/RealTimeTimeSeries/model/attributes_member.py
fds/sdk/RealTimeTimeSeries/model/cursor_based_pagination_output_object_without_total.py
fds/sdk/RealTimeTimeSeries/model/inline_response200.py
fds/sdk/RealTimeTimeSeries/model/inline_response2001.py
fds/sdk/RealTimeTimeSeries/model/inline_response20010.py
fds/sdk/RealTimeTimeSeries/model/inline_response20010_data.py
fds/sdk/RealTimeTimeSeries/model/inline_response20010_data_range.py
fds/sdk/RealTimeTimeSeries/model/inline_response2001_data.py
fds/sdk/RealTimeTimeSeries/model/inline_response2001_meta.py
fds/sdk/RealTimeTimeSeries/model/inline_response2002.py
fds/sdk/RealTimeTimeSeries/model/inline_response2002_data.py
fds/sdk/RealTimeTimeSeries/model/inline_response2002_data_range.py
fds/sdk/RealTimeTimeSeries/model/inline_response2003.py
fds/sdk/RealTimeTimeSeries/model/inline_response2003_data.py
fds/sdk/RealTimeTimeSeries/model/inline_response2004.py
fds/sdk/RealTimeTimeSeries/model/inline_response2004_data.py
fds/sdk/RealTimeTimeSeries/model/inline_response2004_data_range.py
fds/sdk/RealTimeTimeSeries/model/inline_response2005.py
fds/sdk/RealTimeTimeSeries/model/inline_response2005_data.py
fds/sdk/RealTimeTimeSeries/model/inline_response2005_data_range.py
fds/sdk/RealTimeTimeSeries/model/inline_response2006.py
fds/sdk/RealTimeTimeSeries/model/inline_response2006_data.py
fds/sdk/RealTimeTimeSeries/model/inline_response2006_data_subsample.py
fds/sdk/RealTimeTimeSeries/model/inline_response2007.py
fds.sdk.RealTimeTimeSeries-0.20.1.dist-info/LICENSE
fds.sdk.RealTimeTimeSeries-0.20.1.dist-info/METADATA
fds.sdk.RealTimeTimeSeries-0.20.1.dist-info/WHEEL
fds.sdk.RealTimeTimeSeries-0.20.1.dist-info/top_level.txt
fds.sdk.RealTimeTimeSeries-0.20.1.dist-info/RECORD
